qckit/__init__.py
qckit/_settings.py
qckit/configure.py
qckit/benchmarks/__init__.py
qckit/benchmarks/qasmbenchmark.py
qckit/benchmarks/utils.py
qckit/benchmarks/metric/__init__.py
qckit/benchmarks/metric/pulsemetric.py
qckit/circuit/__init__.py
qckit/circuit/library/__init__.py
qckit/circuit/library/bernstein_vazirani.py
qckit/circuit/library/deutsch_jozsa.py
qckit/circuit/library/fourier.py
qckit/circuit/library/grover.py
qckit/circuit/library/random_circuit.py
qckit/circuit/library/utils.py
qckit/credential/__init__.py
qckit/credential/credential.py
qckit/pulse/__init__.py
qckit/pulse/channel.py
qckit/pulse/amptimeseries/__init__.py
qckit/pulse/amptimeseries/amptimeseries.py
qckit/pulse/amptimeseries/circamptimeseries.py
qckit/pulse/amptimeseries/metric.py
qckit/pulse/basispulse/__init__.py
qckit/pulse/basispulse/basispulse.py
qckit/pulse/bosonic/__init__.py
qckit/pulse/bosonic/circuit.py
qckit/pulse/bosonic/sched.py
qckit/pulse/reconstruct/__init__.py
qckit/pulse/reconstruct/perchannelreconstructor.py
qckit-0.0.1.dist-info/LICENSE
qckit-0.0.1.dist-info/METADATA
qckit-0.0.1.dist-info/WHEEL
qckit-0.0.1.dist-info/top_level.txt
qckit-0.0.1.dist-info/RECORD
